odoo/addons/purchase_receipt_expectation_manual/README.rst
odoo/addons/purchase_receipt_expectation_manual/__init__.py
odoo/addons/purchase_receipt_expectation_manual/__manifest__.py
odoo/addons/purchase_receipt_expectation_manual/i18n/fr.po
odoo/addons/purchase_receipt_expectation_manual/i18n/purchase_receipt_expectation_manual.pot
odoo/addons/purchase_receipt_expectation_manual/models/__init__.py
odoo/addons/purchase_receipt_expectation_manual/models/purchase_order.py
odoo/addons/purchase_receipt_expectation_manual/models/purchase_order_line.py
odoo/addons/purchase_receipt_expectation_manual/models/stock_move.py
odoo/addons/purchase_receipt_expectation_manual/readme/CONTRIBUTORS.rst
odoo/addons/purchase_receipt_expectation_manual/readme/DESCRIPTION.rst
odoo/addons/purchase_receipt_expectation_manual/readme/USAGE.rst
odoo/addons/purchase_receipt_expectation_manual/security/ir.model.access.csv
odoo/addons/purchase_receipt_expectation_manual/static/description/icon.png
odoo/addons/purchase_receipt_expectation_manual/static/description/index.html
odoo/addons/purchase_receipt_expectation_manual/tests/__init__.py
odoo/addons/purchase_receipt_expectation_manual/tests/test_purchase_receipt_expectation_manual.py
odoo/addons/purchase_receipt_expectation_manual/views/purchase_order.xml
odoo/addons/purchase_receipt_expectation_manual/wizards/__init__.py
odoo/addons/purchase_receipt_expectation_manual/wizards/purchase_order_manual_receipt.py
odoo/addons/purchase_receipt_expectation_manual/wizards/purchase_order_manual_receipt.xml
odoo/addons/purchase_receipt_expectation_manual/wizards/purchase_order_manual_receipt_line.py
odoo_addon_purchase_receipt_expectation_manual-15.0.1.0.1.2.dist-info/METADATA
odoo_addon_purchase_receipt_expectation_manual-15.0.1.0.1.2.dist-info/WHEEL
odoo_addon_purchase_receipt_expectation_manual-15.0.1.0.1.2.dist-info/top_level.txt
odoo_addon_purchase_receipt_expectation_manual-15.0.1.0.1.2.dist-info/RECORD
